setup.py
config/__init__.py
corevpn/__init__.py
corevpn/app.py
corevpn.egg-info/PKG-INFO
corevpn.egg-info/SOURCES.txt
corevpn.egg-info/dependency_links.txt
corevpn.egg-info/requires.txt
corevpn.egg-info/top_level.txt
corevpn/agents/__init__.py
corevpn/agents/vpn.py
corevpn/hooks/__init__.py
corevpn/hooks/vpn.py
corevpn/models/__init__.py
corevpn/models/vpn/__init__.py
corevpn/models/vpn/vpn.py
corevpn/views/__init__.py
corevpn/views/api/__init__.py
corevpn/views/api/vpn.py