Metadata-Version: 1.1
Name: corevpn
Version: 16.6.1
Summary: CloudOver VPN service
Home-page: http://cloudover.org/corecluster/
Author: Marta Nabozny
Author-email: marta.nabozny@cloudover.io
License: UNKNOWN
Download-URL: https://github.com/cloudOver/CoreVpn/archive/master.zip
Keywords: corecluster,cloudover,cloud,vpn
Platform: UNKNOWN
